SQLITEWRAP/__init__.py
SQLITEWRAP/sqlitewrap.py
SQLITEWRAP-0.0.5.dist-info/LICENSE
SQLITEWRAP-0.0.5.dist-info/METADATA
SQLITEWRAP-0.0.5.dist-info/WHEEL
SQLITEWRAP-0.0.5.dist-info/top_level.txt
SQLITEWRAP-0.0.5.dist-info/RECORD
